simple_ioc/__init__.py
simple_ioc/container.py
simple_ioc-3.0.dist-info/LICENSE
simple_ioc-3.0.dist-info/METADATA
simple_ioc-3.0.dist-info/WHEEL
simple_ioc-3.0.dist-info/top_level.txt
simple_ioc-3.0.dist-info/RECORD
