Metadata-Version: 2.1
Name: simple-ioc
Version: 3.0
Summary: A lightweight library with an implementation of IoC
Home-page: https://github.com/agroptima/simple-ioc
Author: Agroptima S.L.
Author-email: developers@agroptima.com
License: GPLv3
Download-URL: https://github.com/agroptima/simple-ioc/releases
Keywords: python,dependency-injection,inversion-of-control
Platform: UNKNOWN
Classifier: Development Status :: 5 - Production/Stable
Classifier: Intended Audience :: Developers
Classifier: License :: OSI Approved :: GNU General Public License v3 (GPLv3)
Classifier: Natural Language :: English
Classifier: Operating System :: OS Independent
Classifier: Programming Language :: Python
Classifier: Topic :: Utilities
